transliteration/__init__.py
transliteration/transliterate.py
nickffs_transliteration-0.0.9.dist-info/LICENSE
nickffs_transliteration-0.0.9.dist-info/METADATA
nickffs_transliteration-0.0.9.dist-info/WHEEL
nickffs_transliteration-0.0.9.dist-info/top_level.txt
nickffs_transliteration-0.0.9.dist-info/RECORD
