Metadata-Version: 2.1
Name: nickffs-transliteration
Version: 0.0.9
Summary: Hinglish --> Hindi transliteration
Home-page: https://github.com/Bhavnicksm/nickffs-transliteration
Author: bhavnicksm
Author-email: bhavnicksm@gmail.com
License: UNKNOWN
Project-URL: Bug Tracker, https://github.com/Bhavnicksm/nickffs-transliteration/issues
Keywords: Artificial Intelligence,Transliteration,PyTorch,Hindi,Hinglish
Platform: UNKNOWN
Classifier: Programming Language :: Python :: 3
Classifier: License :: OSI Approved :: MIT License
Classifier: Operating System :: OS Independent
Requires-Python: >=3.6
Requires-Dist: torch (>=1.6)
Requires-Dist: torchtext (>=0.8)
